CaboCha.py
_CaboCha.cp38-win32.pyd
cabocha_python-0.69.1.data/data/lib/site-packages/libcabocha.dll
cabocha_python-0.69.1.data/data/lib/site-packages/libcrfpp.dll
cabocha_python-0.69.1.dist-info/METADATA
cabocha_python-0.69.1.dist-info/WHEEL
cabocha_python-0.69.1.dist-info/top_level.txt
cabocha_python-0.69.1.dist-info/RECORD
